mymatchstick2023.py
mymatchstick2023-1.0.0.dist-info/METADATA
mymatchstick2023-1.0.0.dist-info/WHEEL
mymatchstick2023-1.0.0.dist-info/top_level.txt
mymatchstick2023-1.0.0.dist-info/RECORD
