Metadata-Version: 2.1
Name: mymatchstick2023
Version: 1.0.0
Summary: 计算摆放一个自然数需要多少根火柴棒
Home-page: UNKNOWN
Author: xfrszrsfr
Author-email: xfrszrsfr@163.com
License: UNKNOWN
Platform: UNKNOWN
